TotalCoursePoints/__init__.py
TotalCoursePoints/assignment.py
TotalCoursePoints/category.py
TotalCoursePoints/classroom.py
TotalCoursePoints/grade_bins.py
TotalCoursePoints/group.py
TotalCoursePoints/student.py
TotalCoursePoints/utils.py
TotalCoursePoints-1.1.0.dist-info/LICENSE
TotalCoursePoints-1.1.0.dist-info/METADATA
TotalCoursePoints-1.1.0.dist-info/WHEEL
TotalCoursePoints-1.1.0.dist-info/top_level.txt
TotalCoursePoints-1.1.0.dist-info/RECORD
