Metadata-Version: 2.1
Name: TotalCoursePoints
Version: 1.1.0
Summary: This is the backend which makes generating student grades easier.
Home-page: UNKNOWN
Author: Stephan Kaminsky
Author-email: skaminsky115@berkeley.edu
License: MIT
Platform: UNKNOWN
Requires-Dist: numpy
Requires-Dist: pandas
Requires-Dist: pytz
Requires-Dist: gspread
Requires-Dist: oauth2client
